README.txt
setup.cfg
setup.py
docs/HISTORY.txt
docs/INSTALL.txt
docs/LICENSE.GPL
docs/LICENSE.txt
jyu/__init__.py
jyu.pathkey.egg-info/PKG-INFO
jyu.pathkey.egg-info/SOURCES.txt
jyu.pathkey.egg-info/dependency_links.txt
jyu.pathkey.egg-info/entry_points.txt
jyu.pathkey.egg-info/namespace_packages.txt
jyu.pathkey.egg-info/not-zip-safe
jyu.pathkey.egg-info/requires.txt
jyu.pathkey.egg-info/top_level.txt
jyu/pathkey/README.txt
jyu/pathkey/__init__.py
jyu/pathkey/aftertraverse.py
jyu/pathkey/configure.zcml
jyu/pathkey/functions.py
jyu/pathkey/interfaces.py
jyu/pathkey/tests.py
jyu/pathkey/utils.py
jyu/pathkey/browser/__init__.py
jyu/pathkey/browser/configure.zcml
jyu/pathkey/browser/controlpanel.py
jyu/pathkey/browser/pathkeyForm.py
jyu/pathkey/browser/pathkeyList.py
jyu/pathkey/browser/pathkey_requester.pt
jyu/pathkey/browser/pathkeylist_view.pt
jyu/pathkey/browser/set_pathkey.pt
jyu/pathkey/locales/jyu.pathkey.pot
jyu/pathkey/locales/fi/LC_MESSAGES/jyu.pathkey.po
jyu/pathkey/profiles/default/actions.xml
jyu/pathkey/profiles/default/componentregistry.xml
jyu/pathkey/profiles/default/controlpanel.xml
jyu/pathkey/profiles/default/metadata.xml
jyu/pathkey/profiles/default/toolset.xml
jyu/pathkey/profiles/uninstall/actions.xml
jyu/pathkey/tests/__init__.py
jyu/pathkey/tests/base.py
jyu/pathkey/tests/tests_doctests.py