Metadata-Version: 1.0
Name: jyu.pathkey
Version: 1.1.3
Summary: Restricts access to Plone content without proper pathkey
Home-page: http://svn.plone.org/svn/collective/jyu.pathkey
Author: Jukka Ojaniemi
Author-email: jukka.ojaniemi@jyu.fi
License: GPL
Keywords: jyu.pathkey pathkey restrict
Platform: UNKNOWN
Classifier: Framework :: Plone
Classifier: Programming Language :: Python
Classifier: Topic :: Software Development :: Libraries :: Python Modules
